<?xml version="1.0" encoding="utf-8"?>
<openerp>
	<data noupdate="False">

		<record id="res_country_state_ch_ag" model="res.country.state">
			<field name="country_id" search="[('code', '=', 'CH')]" model="res.country" />
			<field name="code">AG</field>
			<field name="name">Aargau</field>
		</record>

		<record id="res_country_state_ch_ai" model="res.country.state">
			<field name="country_id" search="[('code', '=', 'CH')]" model="res.country" />
			<field name="code">AI</field>
			<field name="name">Appenzell Innerrhoden</field>
		</record>

		<record id="res_country_state_ch_ar" model="res.country.state">
			<field name="country_id" search="[('code', '=', 'CH')]" model="res.country" />
			<field name="code">AR</field>
			<field name="name">Appenzell Ausserrhoden</field>
		</record>

		<record id="res_country_state_ch_be" model="res.country.state">
			<field name="country_id" search="[('code', '=', 'CH')]" model="res.country" />
			<field name="code">BE</field>
			<field name="name">Bern</field>
		</record>

		<record id="res_country_state_ch_bl" model="res.country.state">
			<field name="country_id" search="[('code', '=', 'CH')]" model="res.country" />
			<field name="code">BL</field>
			<field name="name">Basel-Landschaft</field>
		</record>

		<record id="res_country_state_ch_bs" model="res.country.state">
			<field name="country_id" search="[('code', '=', 'CH')]" model="res.country" />
			<field name="code">BS</field>
			<field name="name">Basel-Stadt</field>
		</record>

		<record id="res_country_state_ch_fr" model="res.country.state">
			<field name="country_id" search="[('code', '=', 'CH')]" model="res.country" />
			<field name="code">FR</field>
			<field name="name">Fribourg</field>
		</record>

		<record id="res_country_state_ch_ge" model="res.country.state">
			<field name="country_id" search="[('code', '=', 'CH')]" model="res.country" />
			<field name="code">GE</field>
			<field name="name">Geneva</field>
		</record>

		<record id="res_country_state_ch_gl" model="res.country.state">
			<field name="country_id" search="[('code', '=', 'CH')]" model="res.country" />
			<field name="code">GL</field>
			<field name="name">Glarus</field>
		</record>

		<record id="res_country_state_ch_gr" model="res.country.state">
			<field name="country_id" search="[('code', '=', 'CH')]" model="res.country" />
			<field name="code">GR</field>
			<field name="name">Graubünden</field>
		</record>

		<record id="res_country_state_ch_ju" model="res.country.state">
			<field name="country_id" search="[('code', '=', 'CH')]" model="res.country" />
			<field name="code">JU</field>
			<field name="name">Jura</field>
		</record>

		<record id="res_country_state_ch_lu" model="res.country.state">
			<field name="country_id" search="[('code', '=', 'CH')]" model="res.country" />
			<field name="code">LU</field>
			<field name="name">Lucerne</field>
		</record>

		<record id="res_country_state_ch_ne" model="res.country.state">
			<field name="country_id" search="[('code', '=', 'CH')]" model="res.country" />
			<field name="code">NE</field>
			<field name="name">Neuchâtel</field>
		</record>

		<record id="res_country_state_ch_nw" model="res.country.state">
			<field name="country_id" search="[('code', '=', 'CH')]" model="res.country" />
			<field name="code">NW</field>
			<field name="name">Nidwalden</field>
		</record>

		<record id="res_country_state_ch_ow" model="res.country.state">
			<field name="country_id" search="[('code', '=', 'CH')]" model="res.country" />
			<field name="code">OW</field>
			<field name="name">Obwalden</field>
		</record>

		<record id="res_country_state_ch_sg" model="res.country.state">
			<field name="country_id" search="[('code', '=', 'CH')]" model="res.country" />
			<field name="code">SG</field>
			<field name="name">St. Gallen</field>
		</record>

		<record id="res_country_state_ch_sh" model="res.country.state">
			<field name="country_id" search="[('code', '=', 'CH')]" model="res.country" />
			<field name="code">SH</field>
			<field name="name">Schaffhausen</field>
		</record>

		<record id="res_country_state_ch_so" model="res.country.state">
			<field name="country_id" search="[('code', '=', 'CH')]" model="res.country" />
			<field name="code">SO</field>
			<field name="name">Solothurn</field>
		</record>

		<record id="res_country_state_ch_sz" model="res.country.state">
			<field name="country_id" search="[('code', '=', 'CH')]" model="res.country" />
			<field name="code">SZ</field>
			<field name="name">Schwyz</field>
		</record>

		<record id="res_country_state_ch_tg" model="res.country.state">
			<field name="country_id" search="[('code', '=', 'CH')]" model="res.country" />
			<field name="code">TG</field>
			<field name="name">Thurgau</field>
		</record>

		<record id="res_country_state_ch_ti" model="res.country.state">
			<field name="country_id" search="[('code', '=', 'CH')]" model="res.country" />
			<field name="code">TI</field>
			<field name="name">Ticino</field>
		</record>

		<record id="res_country_state_ch_ur" model="res.country.state">
			<field name="country_id" search="[('code', '=', 'CH')]" model="res.country" />
			<field name="code">UR</field>
			<field name="name">Uri</field>
		</record>

		<record id="res_country_state_ch_vd" model="res.country.state">
			<field name="country_id" search="[('code', '=', 'CH')]" model="res.country" />
			<field name="code">VD</field>
			<field name="name">Vaud</field>
		</record>

		<record id="res_country_state_ch_vs" model="res.country.state">
			<field name="country_id" search="[('code', '=', 'CH')]" model="res.country" />
			<field name="code">VS</field>
			<field name="name">Valais</field>
		</record>

		<record id="res_country_state_ch_zg" model="res.country.state">
			<field name="country_id" search="[('code', '=', 'CH')]" model="res.country" />
			<field name="code">ZG</field>
			<field name="name">Zug</field>
		</record>

		<record id="res_country_state_ch_zh" model="res.country.state">
			<field name="country_id" search="[('code', '=', 'CH')]" model="res.country" />
			<field name="code">ZH</field>
			<field name="name">Zurich</field>
		</record>

		<record id="res_country_state_ch_fl" model="res.country.state">
			<field name="country_id" search="[('code', '=', 'CH')]" model="res.country" />
			<field name="code">FL</field>
			<field name="name">Principality of Liechtenstein</field>
		</record>
		
		<record id="res_country_state_ch_de" model="res.country.state">
			<field name="country_id" search="[('code', '=', 'CH')]" model="res.country" />
			<field name="code">DE</field>
			<field name="name">Germany (only for 8238 Büsingen)</field>
		</record>
		
		<record id="res_country_state_ch_it" model="res.country.state">
			<field name="country_id" search="[('code', '=', 'CH')]" model="res.country" />
			<field name="code">IT</field>
			<field name="name">Italy (only for 6911 Campione)</field>
		</record>
		
	</data>
</openerp>